sslinfo/__main__.py
sslinfo/args.py
sslinfo/sslclient.py
sslinfo/version.py
sslinfo/view.py
tests/test_version.py
sslinfo-0.0.2.dist-info/LICENSE
sslinfo-0.0.2.dist-info/METADATA
sslinfo-0.0.2.dist-info/WHEEL
sslinfo-0.0.2.dist-info/entry_points.txt
sslinfo-0.0.2.dist-info/top_level.txt
sslinfo-0.0.2.dist-info/RECORD
