Metadata-Version: 2.1
Name: sslinfo
Version: 0.0.2
Summary: Print the certificate information for a remote SSL/TLS enabled service
Home-page: https://github.com/joaompinto/sslinfo
Author: João Pinto
Author-email: lamego.pinto@gmail.com
License: MIT
Platform: UNKNOWN
License-File: LICENSE
Requires-Dist: pyopenssl
Requires-Dist: rich
